Metadata-Version: 2.1
Name: brzcode
Version: 1.0.8
Summary: Uma programação simples, completa, e veloz.
Author: Gustavo Martinez
Author-email: gamezinhoo@outlook.com
License: MIT License
Keywords: brzcode
License-File: LICENSE
